pywxdump/WX_OFFS.json
pywxdump/__init__.py
pywxdump/cli.py
pywxdump/analyzer/__init__.py
pywxdump/analyzer/chat_analysis.py
pywxdump/analyzer/cleanup.py
pywxdump/analyzer/utils.py
pywxdump/api/__init__.py
pywxdump/api/local_server.py
pywxdump/api/remote_server.py
pywxdump/api/rjson.py
pywxdump/api/utils.py
pywxdump/api/export/__init__.py
pywxdump/api/export/exportCSV.py
pywxdump/api/export/exportHtml.py
pywxdump/api/export/exportJSON.py
pywxdump/db/__init__.py
pywxdump/db/dbFavorite.py
pywxdump/db/dbMSG.py
pywxdump/db/dbMedia.py
pywxdump/db/dbMicro.py
pywxdump/db/dbOpenIMContact.py
pywxdump/db/dbOpenIMMedia.py
pywxdump/db/dbPublicMsg.py
pywxdump/db/dbSns.py
pywxdump/db/dbbase.py
pywxdump/db/utils/__init__.py
pywxdump/db/utils/_loger.py
pywxdump/db/utils/common_utils.py
pywxdump/ui/__init__.py
pywxdump/ui/web/data.js
pywxdump/ui/web/favicon.ico
pywxdump/ui/web/index.html
pywxdump/ui/web/assets/AboutView-ORn2cSo5.js
pywxdump/ui/web/assets/AboutView-ugaba3L_.css
pywxdump/ui/web/assets/BiasView--tKtwVTQ.js
pywxdump/ui/web/assets/ChatRecprdsHeader-396U3iVd.css
pywxdump/ui/web/assets/ChatView-M5nr1IIW.js
pywxdump/ui/web/assets/CleanupView-3mnnNtqB.js
pywxdump/ui/web/assets/ContactsView-jebgvIRE.js
pywxdump/ui/web/assets/DateTimeSelect-YCtkWrdt.css
pywxdump/ui/web/assets/DbInitComponent.vue_vue_type_script_setup_true_lang-6lZl_8wa.js
pywxdump/ui/web/assets/DbInitView-R4j6njmE.js
pywxdump/ui/web/assets/DecryptView-CXq54gv8.js
pywxdump/ui/web/assets/FavoriteView-sC9Hm1aw.js
pywxdump/ui/web/assets/HelpView-oW8YOXJW.js
pywxdump/ui/web/assets/HomeView-7gTaiNiY.js
pywxdump/ui/web/assets/IndexView-MIpPVMcg.js
pywxdump/ui/web/assets/IndexView.vue_vue_type_script_setup_true_lang-VVdkpyuI.js
pywxdump/ui/web/assets/MergeView-II-oDQUp.js
pywxdump/ui/web/assets/MomentsView-tpqcV7Lh.js
pywxdump/ui/web/assets/SettingView-xYJhDmcm.js
pywxdump/ui/web/assets/StatisticsView-_MI6G2N3.js
pywxdump/ui/web/assets/StatisticsView-wCJVfg9x.css
pywxdump/ui/web/assets/WxinfoView-3TV0JVP6.js
pywxdump-3.1.45.dist-info/LICENSE
pywxdump-3.1.45.dist-info/METADATA
pywxdump-3.1.45.dist-info/WHEEL
pywxdump-3.1.45.dist-info/entry_points.txt
pywxdump-3.1.45.dist-info/top_level.txt
pywxdump-3.1.45.dist-info/RECORD
