Metadata-Version: 2.1
Name: pywxdump
Version: 3.1.45
Summary: 微信信息获取工具
Home-page: https://github.com/xaoyaoo/PyWxDump
Author: xaoyaoo
Author-email: xaoyaoo@gmail.com
License: MIT
Classifier: Programming Language :: Python :: 3
Classifier: Operating System :: OS Independent
Requires-Python: >=3.8, <4
License-File: LICENSE
Requires-Dist: psutil
Requires-Dist: pycryptodomex
Requires-Dist: pywin32
Requires-Dist: pymem
Requires-Dist: silk-python
Requires-Dist: pyaudio
Requires-Dist: requests
Requires-Dist: pyahocorasick
Requires-Dist: lz4
Requires-Dist: blackboxprotobuf
Requires-Dist: lxml
Requires-Dist: dbutils
Requires-Dist: fastapi
Requires-Dist: uvicorn
Requires-Dist: python-dotenv
